examples/__init__.py
examples/demo.py
examples/demo_settings.py
examples/demonstration/__init__.py
examples/demonstration/custom_tool.py
examples/demonstration/demo_text.py
examples/demonstration/demo_window.py
examples/demonstration/hooks_editor.py
examples/demonstration/hooks_examples.py
examples/demonstration/workers.py
examples/demonstration/catalog/__init__.py
examples/demonstration/catalog/builders.py
examples/demonstration/catalog/dock.py
examples/demonstration/catalog/models.py
examples/demonstration/config/__init__.py
examples/demonstration/config/dialog.py
examples/demonstration/config/spec.py
examples/demonstration/extension_examples/custom_cursor.py
examples/demonstration/extension_examples/custom_overlay.py
examples/demonstration/extension_examples/lens_tool.py
qpane/__init__.py
qpane/_version.py
qpane/qpane.py
qpane/qpane.pyi
qpane/types.py
qpane/cache/__init__.py
qpane/cache/consumers.py
qpane/cache/coordinator.py
qpane/cache/diagnostics.py
qpane/cache/registry.py
qpane/catalog/__init__.py
qpane/catalog/catalog.py
qpane/catalog/controller.py
qpane/catalog/image_catalog.py
qpane/catalog/image_map.py
qpane/catalog/image_utils.py
qpane/catalog/link.py
qpane/concurrency/__init__.py
qpane/concurrency/base_worker.py
qpane/concurrency/executor.py
qpane/concurrency/metrics.py
qpane/concurrency/retry.py
qpane/concurrency/retry_view.py
qpane/concurrency/thread_policy.py
qpane/core/__init__.py
qpane/core/config.py
qpane/core/config_features.py
qpane/core/diagnostics.py
qpane/core/diagnostics_broker.py
qpane/core/fallbacks.py
qpane/core/feature_coordinator.py
qpane/core/hooks.py
qpane/core/state.py
qpane/core/threading.py
qpane/features/__init__.py
qpane/features/registry.py
qpane/masks/__init__.py
qpane/masks/autosave.py
qpane/masks/delegate.py
qpane/masks/install.py
qpane/masks/mask.py
qpane/masks/mask_controller.py
qpane/masks/mask_diagnostics.py
qpane/masks/mask_service.py
qpane/masks/mask_undo.py
qpane/masks/sam_feature.py
qpane/masks/stroke_render.py
qpane-1.2.1.dist-info/licenses/LICENSE
qpane-1.2.1.dist-info/METADATA
qpane-1.2.1.dist-info/WHEEL
qpane-1.2.1.dist-info/top_level.txt
qpane-1.2.1.dist-info/RECORD
