Metadata-Version: 2.4
Name: qpane
Version: 1.2.1
Summary: High-performance Qt image viewer with pan, zoom, and tile-based rendering
Author-email: Artificial Sweetener <artificialsweetenerai@proton.me>
License: GPL-3.0-only
Project-URL: Homepage, https://artificialsweetener.ai
Project-URL: Repository, https://github.com/Artificial-Sweetener/QPane
Project-URL: Issues, https://github.com/Artificial-Sweetener/QPane/issues
Project-URL: Documentation, https://github.com/Artificial-Sweetener/QPane/tree/main/docs
Classifier: License :: OSI Approved :: GNU General Public License v3 (GPLv3)
Classifier: Operating System :: OS Independent
Classifier: Programming Language :: Python :: 3
Classifier: Programming Language :: Python :: 3.10
Classifier: Programming Language :: Python :: 3.11
Classifier: Programming Language :: Python :: 3.12
Classifier: Topic :: Multimedia :: Graphics
Classifier: Topic :: Scientific/Engineering :: Image Processing
Requires-Python: >=3.10
License-File: LICENSE
Requires-Dist: PySide6>=6.7.3
Requires-Dist: numpy>=1.21
Requires-Dist: psutil>=5.9
Provides-Extra: mask
Requires-Dist: opencv-python>=4.9; extra == "mask"
Provides-Extra: sam
Requires-Dist: opencv-python>=4.9; extra == "sam"
Requires-Dist: torch>=2.1; extra == "sam"
Requires-Dist: mobilesam-mirror>=1.0.0; extra == "sam"
Requires-Dist: timm>=0.9; extra == "sam"
Provides-Extra: full
Requires-Dist: opencv-python>=4.9; extra == "full"
Requires-Dist: torch>=2.1; extra == "full"
Requires-Dist: mobilesam-mirror>=1.0.0; extra == "full"
Requires-Dist: timm>=0.9; extra == "full"
Provides-Extra: dev
Requires-Dist: opencv-python>=4.9; extra == "dev"
Requires-Dist: torch>=2.1; extra == "dev"
Requires-Dist: mobilesam-mirror>=1.0.0; extra == "dev"
Requires-Dist: timm>=0.9; extra == "dev"
Requires-Dist: pytest; extra == "dev"
Requires-Dist: pytest-xdist>=3.8.0; extra == "dev"
Requires-Dist: ruff; extra == "dev"
Requires-Dist: black; extra == "dev"
Requires-Dist: python-semantic-release; extra == "dev"
Dynamic: license-file
